Metadata-Version: 2.1
Name: weather-reporter
Version: 1.0.1
Summary: A Python package to get weather reports for any location.
Home-page: https://github.com/nikhilkumarsingh/weather-reporter
Author: Nikhil Kumar Singh
Author-email: nikhilksingh97@gmail.com
License: MIT
Platform: UNKNOWN
Classifier: License :: OSI Approved :: MIT License
Classifier: Programming Language :: Python :: 3
Classifier: Programming Language :: Python :: 3.7
Requires-Dist: requests
